{"TRANSACTION_ID": "TXN-8f36507a", "TIMESTAMP": "2025-03-24T11:23:45.125281Z", "USER_ID": "USER-9452", "USER_NAME": "Joseph", "PRODUCT_ID": "PROD-355", "AMOUNT": 797.91, "CURRENCY": "GBP", "TRANSACTION_TYPE": "refund", "STATUS": "failed", "LOCATION_CITY": "Munich", "LOCATION_COUNTRY": "Germany", "PAYMENT_METHOD": "google_pay", "PRODUCT_CATEGORY": "food", "QUANTITY": 8, "SHIPPING_STREET": "839 Main St", "SHIPPING_ZIP": "97030", "SHIPPING_CITY": "Munich", "SHIPPING_COUNTRY": "Germany", "DEVICE_OS": "Android", "DEVICE_BROWSER": "Firefox", "DEVICE_IP": "70.225.114.98", "CUSTOMER_RATING": null, "DISCOUNT_CODE": "DISCOUNT-431", "TAX_AMOUNT": 0.0, "THREAD": 0, "MESSAGE_NUMBER": 3, "TIMESTAMP_OF_RECEPTION_LOG": "07/04/2025 14:10:23"}